approxbayescomp/__init__.py
approxbayescomp/attempted_fast_pdf_prior.py
approxbayescomp/distance.py
approxbayescomp/new_smc.py
approxbayescomp/plot.py
approxbayescomp/population.py
approxbayescomp/prior.py
approxbayescomp/psi.py
approxbayescomp/simulate.py
approxbayescomp/smc.py
approxbayescomp/utils.py
approxbayescomp/weighted.py
approxbayescomp-0.2.1.dist-info/METADATA
approxbayescomp-0.2.1.dist-info/WHEEL
approxbayescomp-0.2.1.dist-info/top_level.txt
approxbayescomp-0.2.1.dist-info/RECORD
